fasd/__init__.py
fasd/base.py
fasd/mlp.py
fasd/model.py
fasd/model_components.py
fasd/utils.py
fasd-0.1.3.dist-info/licenses/LICENSE
fasd-0.1.3.dist-info/METADATA
fasd-0.1.3.dist-info/WHEEL
fasd-0.1.3.dist-info/top_level.txt
fasd-0.1.3.dist-info/RECORD
