Metadata-Version: 2.4
Name: fasd
Version: 0.1.3
Summary: Pytorch model for generating fidelity agnostic synthetic data
Author: Jim Achterberg
Author-email: j.l.achterberg@lumc.nl
Classifier: Programming Language :: Python :: 3
Classifier: License :: OSI Approved :: MIT License
Classifier: Operating System :: OS Independent
Requires-Python: >=3.8
License-File: LICENSE
Requires-Dist: torch
Requires-Dist: pandas
Requires-Dist: scikit-learn
Requires-Dist: tqdm
Dynamic: author
Dynamic: author-email
Dynamic: classifier
Dynamic: description
Dynamic: description-content-type
Dynamic: license-file
Dynamic: requires-dist
Dynamic: requires-python
Dynamic: summary
